mml/__init__.py
mml/__main__.py
mml/cli.py
mml/template.env
mml/api/__init__.py
mml/configs/__init__.py
mml/configs/config_mml.yaml
mml/configs/arch/smp.yaml
mml/configs/arch/timm.yaml
mml/configs/augmentations/base_rand.yaml
mml/configs/augmentations/baseline256.yaml
mml/configs/augmentations/baseline512.yaml
mml/configs/augmentations/basic.yaml
mml/configs/augmentations/default.yaml
mml/configs/augmentations/kornia.yaml
mml/configs/augmentations/load_imagenet_aa.yaml
mml/configs/augmentations/no_norm.yaml
mml/configs/augmentations/none.yaml
mml/configs/augmentations/randaugment.yaml
mml/configs/augmentations/v2.yaml
mml/configs/callbacks/cutmix.yaml
mml/configs/callbacks/default.yaml
mml/configs/callbacks/early.yaml
mml/configs/callbacks/mixup.yaml
mml/configs/callbacks/none.yaml
mml/configs/callbacks/stats.yaml
mml/configs/callbacks/swa.yaml
mml/configs/compile/default.yaml
mml/configs/hpo/default.yaml
mml/configs/hpo/grid.yaml
mml/configs/hpo/sampler/grid.yaml
mml/configs/hpo/sampler/random.yaml
mml/configs/hpo/sampler/tpe.yaml
mml/configs/hydra/help/mml_help.yaml
mml/configs/hydra/hydra_logging/col_stdout.yaml
mml/configs/hydra/job_logging/col_stdout_and_file.yaml
mml/configs/hydra/job_logging/rich_stdout_and_file.yaml
mml/configs/hydra/job_logging/stdout_only.yaml
mml/configs/loaders/default.yaml
mml/configs/loaders/numpy.yaml
mml/configs/loaders/pillow.yaml
mml/configs/loaders/pillow_acc.yaml
mml/configs/loaders/scikit.yaml
mml/configs/loaders/torch.yaml
mml/configs/loaders/uni.yaml
mml/configs/logging/log.yaml
mml/configs/logging/exp_logger/tensorboard.yaml
mml/configs/logging/notifier/email.yaml
mml/configs/logging/notifier/none.yaml
mml/configs/logging/notifier/slack.yaml
mml/configs/logging/render/colorlog.yaml
mml/configs/logging/render/rich.yaml
mml/configs/loss/default.yaml
mml/configs/loss/cls/ce.yaml
mml/configs/loss/mlcls/bce.yaml
mml/configs/loss/mlcls/ce.yaml
mml/configs/loss/reg/huber.yaml
mml/configs/loss/seg/ce.yaml
mml_core-1.0.4.dist-info/licenses/LICENSE
mml_core-1.0.4.dist-info/METADATA
mml_core-1.0.4.dist-info/WHEEL
mml_core-1.0.4.dist-info/entry_points.txt
mml_core-1.0.4.dist-info/top_level.txt
mml_core-1.0.4.dist-info/RECORD
