Metadata-Version: 2.4
Name: mml-core
Version: 1.0.4
Summary: This is the MML toolkit, targeting lifelong/continual/meta learning in Surgical Data Science.
Home-page: https://github.com/IMSY-DKFZ/mml
Author: Patrick Godau
Author-email: patrick.godau@dkfz-heidelberg.de
License: MIT
Project-URL: Documentation, https://mml.readthedocs.io
Project-URL: Bug Reports, https://github.com/IMSY-DKFZ/mml/issues
Classifier: Natural Language :: English
Classifier: Development Status :: 4 - Beta
Classifier: Environment :: Console
Classifier: Environment :: GPU
Classifier: Intended Audience :: Developers
Classifier: Intended Audience :: Science/Research
Classifier: Topic :: Scientific/Engineering :: Artificial Intelligence
Classifier: Topic :: Scientific/Engineering :: Image Recognition
Classifier: Topic :: Scientific/Engineering :: Information Analysis
Classifier: Topic :: Scientific/Engineering :: Image Processing
Classifier: Topic :: Software Development :: Libraries :: Application Frameworks
Classifier: Topic :: Software Development :: Libraries :: Python Modules
Classifier: Topic :: Software Development :: Version Control :: Git
Classifier: Operating System :: OS Independent
Classifier: Programming Language :: Python :: 3
Classifier: Programming Language :: Python :: 3.8
Classifier: Programming Language :: Python :: 3.9
Classifier: Programming Language :: Python :: 3.10
Classifier: Typing :: Typed
Classifier: License :: OSI Approved :: MIT License
Requires-Python: >=3.10
License-File: LICENSE
Requires-Dist: torch
Requires-Dist: torchvision
Requires-Dist: torchmetrics
Requires-Dist: segmentation-models-pytorch==0.3.3
Requires-Dist: plotly
Requires-Dist: statsmodels==0.13.5
Requires-Dist: matplotlib
Requires-Dist: lightning
Requires-Dist: tensorboard
Requires-Dist: albumentations==2.0.5
Requires-Dist: pandas
Requires-Dist: hydra-core==1.3.2
Requires-Dist: hydra-colorlog
Requires-Dist: hydra-optuna-sweeper>=1.2
Requires-Dist: python-dotenv
Requires-Dist: rarfile
Requires-Dist: colorama
Requires-Dist: p-tqdm==1.4.0
Requires-Dist: orjson==3.9.2
Requires-Dist: ijson
Requires-Dist: scikit-learn
Requires-Dist: scikit-image
Requires-Dist: kaggle==1.5.15
Requires-Dist: setuptools
Requires-Dist: Deprecated
Requires-Dist: pytest==7.4.0
Requires-Dist: kornia
Requires-Dist: rich
Requires-Dist: prettytable
Requires-Dist: jupyter
Requires-Dist: humanize
Requires-Dist: psrcal==0.0.2
Requires-Dist: quapy==0.1.9
Provides-Extra: dev
Requires-Dist: pytest-console-scripts; extra == "dev"
Requires-Dist: pytest-cov; extra == "dev"
Requires-Dist: pytest-benchmark; extra == "dev"
Requires-Dist: mypy; extra == "dev"
Requires-Dist: ruff; extra == "dev"
Requires-Dist: pylint; extra == "dev"
Requires-Dist: tox; extra == "dev"
Requires-Dist: isort; extra == "dev"
Requires-Dist: types-requests; extra == "dev"
Requires-Dist: types-Deprecated; extra == "dev"
Requires-Dist: add-license-header; extra == "dev"
Provides-Extra: docs
Requires-Dist: sphinx; extra == "docs"
Requires-Dist: sphinx-rtd-theme; extra == "docs"
Requires-Dist: myst-nb; extra == "docs"
Requires-Dist: sphinxcontrib-autoyaml; extra == "docs"
Requires-Dist: lightning-fabric; extra == "docs"
Dynamic: license-file
